src/__init__.py
src/database.py
src/models.py
src/server.py
iflow_mcp_mcp_server_aact-0.4.0.dist-info/METADATA
iflow_mcp_mcp_server_aact-0.4.0.dist-info/WHEEL
iflow_mcp_mcp_server_aact-0.4.0.dist-info/entry_points.txt
iflow_mcp_mcp_server_aact-0.4.0.dist-info/licenses/LICENSE
iflow_mcp_mcp_server_aact-0.4.0.dist-info/RECORD
