Metadata-Version: 2.4
Name: iflow-mcp_mcp-server-aact
Version: 0.4.0
Summary: MCP server for AACT clinical trials database
License-File: LICENSE
Requires-Python: >=3.10
Requires-Dist: mcp>=1.12.4
Requires-Dist: psycopg2-binary
Requires-Dist: python-dotenv
Provides-Extra: test
Requires-Dist: pytest; extra == 'test'
Requires-Dist: pytest-asyncio; extra == 'test'
